mriqc_learn/__init__.py
mriqc_learn/_version.py
mriqc_learn/data/abide_scan_parameters.tsv
mriqc_learn/data/classifier.joblib
mriqc_learn/data/model_selection.yaml
mriqc_learn/datasets/__init__.py
mriqc_learn/datasets/abide.tsv
mriqc_learn/datasets/ds030.tsv
mriqc_learn/model_selection/__init__.py
mriqc_learn/model_selection/split.py
mriqc_learn/models/__init__.py
mriqc_learn/models/preprocess.py
mriqc_learn/models/production.py
mriqc_learn/viz/__init__.py
mriqc_learn/viz/metrics.py
mriqc_learn/viz/ratings.py
mriqc_learn-0.0.3.dist-info/METADATA
mriqc_learn-0.0.3.dist-info/WHEEL
mriqc_learn-0.0.3.dist-info/licenses/LICENSE
mriqc_learn-0.0.3.dist-info/RECORD
